mle_kit_mcp/__init__.py
mle_kit_mcp/__main__.py
mle_kit_mcp/files.py
mle_kit_mcp/llm_proxy.py
mle_kit_mcp/py.typed
mle_kit_mcp/server.py
mle_kit_mcp/settings.py
mle_kit_mcp/utils.py
mle_kit_mcp/tools/__init__.py
mle_kit_mcp/tools/bash.py
mle_kit_mcp/tools/file_system.py
mle_kit_mcp/tools/llm_proxy.py
mle_kit_mcp/tools/remote_gpu.py
mle_kit_mcp/tools/text_editor.py
mle_kit_mcp-1.2.4.dist-info/licenses/LICENSE
mle_kit_mcp-1.2.4.dist-info/METADATA
mle_kit_mcp-1.2.4.dist-info/WHEEL
mle_kit_mcp-1.2.4.dist-info/entry_points.txt
mle_kit_mcp-1.2.4.dist-info/top_level.txt
mle_kit_mcp-1.2.4.dist-info/RECORD
