Metadata-Version: 2.4
Name: mle-kit-mcp
Version: 1.2.4
Summary: MCP server that provides different tools for MLE
Author-email: Ilya Gusev <phoenixilya@gmail.com>
Project-URL: Homepage, https://github.com/IlyaGusev/mle_kit_mcp
Classifier: Programming Language :: Python :: 3
Classifier: License :: OSI Approved :: MIT License
Classifier: Operating System :: OS Independent
Requires-Python: >=3.12
License-File: LICENSE
Requires-Dist: mcp>=1.9.2
Requires-Dist: fire>=0.7.0
Requires-Dist: docker>=7.1.0
Requires-Dist: vastai-sdk==0.1.16
Requires-Dist: openai>=1.102.0
Requires-Dist: fastapi>=0.116.1
Requires-Dist: pydantic-settings>=2.4.0
Dynamic: license-file
